<?xml version="1.0" encoding="UTF-8"?>
<tv generator-info-name="m3u4u" generator-info-url="https://m3u4u.com/">
<channel id="m3u4u">
<display-name>Visit m3u4u.com</display-name>
</channel>
<programme start="20260129000000 +0000" stop="20260129010000 +0000" channel="m3u4u">
<title lang="en">Visit m3u4u.com</title>
<desc lang="en">Visit m3u4u.com</desc>
</programme>
<programme start="20260129010000 +0000" stop="20260129020000 +0000" channel="m3u4u">
<title lang="en">Visit m3u4u.com</title>
<desc lang="en">Visit m3u4u.com</desc>
</programme>
<programme start="20260129020000 +0000" stop="20260129030000 +0000" channel="m3u4u">
<title lang="en">Visit m3u4u.com</title>
<desc lang="en">Visit m3u4u.com</desc>
</programme>
<programme start="20260129030000 +0000" stop="20260129040000 +0000" channel="m3u4u">
<title lang="en">Visit m3u4u.com</title>
<desc lang="en">Visit m3u4u.com</desc>
</programme>
<programme start="20260129040000 +0000" stop="20260129050000 +0000" channel="m3u4u">
<title lang="en">Visit m3u4u.com</title>
<desc lang="en">Visit m3u4u.com</desc>
</programme>
<programme start="20260129050000 +0000" stop="20260129060000 +0000" channel="m3u4u">
<title lang="en">Visit m3u4u.com</title>
<desc lang="en">Visit m3u4u.com</desc>
</programme>
<programme start="20260129060000 +0000" stop="20260129070000 +0000" channel="m3u4u">
<title lang="en">Visit m3u4u.com</title>
<desc lang="en">Visit m3u4u.com</desc>
</programme>
<programme start="20260129070000 +0000" stop="20260129080000 +0000" channel="m3u4u">
<title lang="en">Visit m3u4u.com</title>
<desc lang="en">Visit m3u4u.com</desc>
</programme>
<programme start="20260129080000 +0000" stop="20260129090000 +0000" channel="m3u4u">
<title lang="en">Visit m3u4u.com</title>
<desc lang="en">Visit m3u4u.com</desc>
</programme>
<programme start="20260129090000 +0000" stop="20260129100000 +0000" channel="m3u4u">
<title lang="en">Visit m3u4u.com</title>
<desc lang="en">Visit m3u4u.com</desc>
</programme>
<programme start="20260129100000 +0000" stop="20260129110000 +0000" channel="m3u4u">
<title lang="en">Visit m3u4u.com</title>
<desc lang="en">Visit m3u4u.com</desc>
</programme>
<programme start="20260129110000 +0000" stop="20260129120000 +0000" channel="m3u4u">
<title lang="en">Visit m3u4u.com</title>
<desc lang="en">Visit m3u4u.com</desc>
</programme>
<programme start="20260129120000 +0000" stop="20260129130000 +0000" channel="m3u4u">
<title lang="en">Visit m3u4u.com</title>
<desc lang="en">Visit m3u4u.com</desc>
</programme>
<programme start="20260129130000 +0000" stop="20260129140000 +0000" channel="m3u4u">
<title lang="en">Visit m3u4u.com</title>
<desc lang="en">Visit m3u4u.com</desc>
</programme>
<programme start="20260129140000 +0000" stop="20260129150000 +0000" channel="m3u4u">
<title lang="en">Visit m3u4u.com</title>
<desc lang="en">Visit m3u4u.com</desc>
</programme>
<programme start="20260129150000 +0000" stop="20260129160000 +0000" channel="m3u4u">
<title lang="en">Visit m3u4u.com</title>
<desc lang="en">Visit m3u4u.com</desc>
</programme>
<programme start="20260129160000 +0000" stop="20260129170000 +0000" channel="m3u4u">
<title lang="en">Visit m3u4u.com</title>
<desc lang="en">Visit m3u4u.com</desc>
</programme>
<programme start="20260129170000 +0000" stop="20260129180000 +0000" channel="m3u4u">
<title lang="en">Visit m3u4u.com</title>
<desc lang="en">Visit m3u4u.com</desc>
</programme>
<programme start="20260129180000 +0000" stop="20260129190000 +0000" channel="m3u4u">
<title lang="en">Visit m3u4u.com</title>
<desc lang="en">Visit m3u4u.com</desc>
</programme>
<programme start="20260129190000 +0000" stop="20260129200000 +0000" channel="m3u4u">
<title lang="en">Visit m3u4u.com</title>
<desc lang="en">Visit m3u4u.com</desc>
</programme>
<programme start="20260129200000 +0000" stop="20260129210000 +0000" channel="m3u4u">
<title lang="en">Visit m3u4u.com</title>
<desc lang="en">Visit m3u4u.com</desc>
</programme>
<programme start="20260129210000 +0000" stop="20260129220000 +0000" channel="m3u4u">
<title lang="en">Visit m3u4u.com</title>
<desc lang="en">Visit m3u4u.com</desc>
</programme>
<programme start="20260129220000 +0000" stop="20260129230000 +0000" channel="m3u4u">
<title lang="en">Visit m3u4u.com</title>
<desc lang="en">Visit m3u4u.com</desc>
</programme>
<programme start="20260129230000 +0000" stop="20260130000000 +0000" channel="m3u4u">
<title lang="en">Visit m3u4u.com</title>
<desc lang="en">Visit m3u4u.com</desc>
</programme>
<programme start="20260130000000 +0000" stop="20260130010000 +0000" channel="m3u4u">
<title lang="en">Visit m3u4u.com</title>
<desc lang="en">Visit m3u4u.com</desc>
</programme>
<programme start="20260130010000 +0000" stop="20260130020000 +0000" channel="m3u4u">
<title lang="en">Visit m3u4u.com</title>
<desc lang="en">Visit m3u4u.com</desc>
</programme>
<programme start="20260130020000 +0000" stop="20260130030000 +0000" channel="m3u4u">
<title lang="en">Visit m3u4u.com</title>
<desc lang="en">Visit m3u4u.com</desc>
</programme>
<programme start="20260130030000 +0000" stop="20260130040000 +0000" channel="m3u4u">
<title lang="en">Visit m3u4u.com</title>
<desc lang="en">Visit m3u4u.com</desc>
</programme>
<programme start="20260130040000 +0000" stop="20260130050000 +0000" channel="m3u4u">
<title lang="en">Visit m3u4u.com</title>
<desc lang="en">Visit m3u4u.com</desc>
</programme>
<programme start="20260130050000 +0000" stop="20260130060000 +0000" channel="m3u4u">
<title lang="en">Visit m3u4u.com</title>
<desc lang="en">Visit m3u4u.com</desc>
</programme>
<programme start="20260130060000 +0000" stop="20260130070000 +0000" channel="m3u4u">
<title lang="en">Visit m3u4u.com</title>
<desc lang="en">Visit m3u4u.com</desc>
</programme>
<programme start="20260130070000 +0000" stop="20260130080000 +0000" channel="m3u4u">
<title lang="en">Visit m3u4u.com</title>
<desc lang="en">Visit m3u4u.com</desc>
</programme>
<programme start="20260130080000 +0000" stop="20260130090000 +0000" channel="m3u4u">
<title lang="en">Visit m3u4u.com</title>
<desc lang="en">Visit m3u4u.com</desc>
</programme>
<programme start="20260130090000 +0000" stop="20260130100000 +0000" channel="m3u4u">
<title lang="en">Visit m3u4u.com</title>
<desc lang="en">Visit m3u4u.com</desc>
</programme>
<programme start="20260130100000 +0000" stop="20260130110000 +0000" channel="m3u4u">
<title lang="en">Visit m3u4u.com</title>
<desc lang="en">Visit m3u4u.com</desc>
</programme>
<programme start="20260130110000 +0000" stop="20260130120000 +0000" channel="m3u4u">
<title lang="en">Visit m3u4u.com</title>
<desc lang="en">Visit m3u4u.com</desc>
</programme>
<programme start="20260130120000 +0000" stop="20260130130000 +0000" channel="m3u4u">
<title lang="en">Visit m3u4u.com</title>
<desc lang="en">Visit m3u4u.com</desc>
</programme>
<programme start="20260130130000 +0000" stop="20260130140000 +0000" channel="m3u4u">
<title lang="en">Visit m3u4u.com</title>
<desc lang="en">Visit m3u4u.com</desc>
</programme>
<programme start="20260130140000 +0000" stop="20260130150000 +0000" channel="m3u4u">
<title lang="en">Visit m3u4u.com</title>
<desc lang="en">Visit m3u4u.com</desc>
</programme>
<programme start="20260130150000 +0000" stop="20260130160000 +0000" channel="m3u4u">
<title lang="en">Visit m3u4u.com</title>
<desc lang="en">Visit m3u4u.com</desc>
</programme>
<programme start="20260130160000 +0000" stop="20260130170000 +0000" channel="m3u4u">
<title lang="en">Visit m3u4u.com</title>
<desc lang="en">Visit m3u4u.com</desc>
</programme>
<programme start="20260130170000 +0000" stop="20260130180000 +0000" channel="m3u4u">
<title lang="en">Visit m3u4u.com</title>
<desc lang="en">Visit m3u4u.com</desc>
</programme>
<programme start="20260130180000 +0000" stop="20260130190000 +0000" channel="m3u4u">
<title lang="en">Visit m3u4u.com</title>
<desc lang="en">Visit m3u4u.com</desc>
</programme>
<programme start="20260130190000 +0000" stop="20260130200000 +0000" channel="m3u4u">
<title lang="en">Visit m3u4u.com</title>
<desc lang="en">Visit m3u4u.com</desc>
</programme>
<programme start="20260130200000 +0000" stop="20260130210000 +0000" channel="m3u4u">
<title lang="en">Visit m3u4u.com</title>
<desc lang="en">Visit m3u4u.com</desc>
</programme>
<programme start="20260130210000 +0000" stop="20260130220000 +0000" channel="m3u4u">
<title lang="en">Visit m3u4u.com</title>
<desc lang="en">Visit m3u4u.com</desc>
</programme>
<programme start="20260130220000 +0000" stop="20260130230000 +0000" channel="m3u4u">
<title lang="en">Visit m3u4u.com</title>
<desc lang="en">Visit m3u4u.com</desc>
</programme>
<programme start="20260130230000 +0000" stop="20260131000000 +0000" channel="m3u4u">
<title lang="en">Visit m3u4u.com</title>
<desc lang="en">Visit m3u4u.com</desc>
</programme>
<programme start="20260131000000 +0000" stop="20260131010000 +0000" channel="m3u4u">
<title lang="en">Visit m3u4u.com</title>
<desc lang="en">Visit m3u4u.com</desc>
</programme>
<programme start="20260131010000 +0000" stop="20260131020000 +0000" channel="m3u4u">
<title lang="en">Visit m3u4u.com</title>
<desc lang="en">Visit m3u4u.com</desc>
</programme>
<programme start="20260131020000 +0000" stop="20260131030000 +0000" channel="m3u4u">
<title lang="en">Visit m3u4u.com</title>
<desc lang="en">Visit m3u4u.com</desc>
</programme>
<programme start="20260131030000 +0000" stop="20260131040000 +0000" channel="m3u4u">
<title lang="en">Visit m3u4u.com</title>
<desc lang="en">Visit m3u4u.com</desc>
</programme>
<programme start="20260131040000 +0000" stop="20260131050000 +0000" channel="m3u4u">
<title lang="en">Visit m3u4u.com</title>
<desc lang="en">Visit m3u4u.com</desc>
</programme>
<programme start="20260131050000 +0000" stop="20260131060000 +0000" channel="m3u4u">
<title lang="en">Visit m3u4u.com</title>
<desc lang="en">Visit m3u4u.com</desc>
</programme>
<programme start="20260131060000 +0000" stop="20260131070000 +0000" channel="m3u4u">
<title lang="en">Visit m3u4u.com</title>
<desc lang="en">Visit m3u4u.com</desc>
</programme>
<programme start="20260131070000 +0000" stop="20260131080000 +0000" channel="m3u4u">
<title lang="en">Visit m3u4u.com</title>
<desc lang="en">Visit m3u4u.com</desc>
</programme>
<programme start="20260131080000 +0000" stop="20260131090000 +0000" channel="m3u4u">
<title lang="en">Visit m3u4u.com</title>
<desc lang="en">Visit m3u4u.com</desc>
</programme>
<programme start="20260131090000 +0000" stop="20260131100000 +0000" channel="m3u4u">
<title lang="en">Visit m3u4u.com</title>
<desc lang="en">Visit m3u4u.com</desc>
</programme>
<programme start="20260131100000 +0000" stop="20260131110000 +0000" channel="m3u4u">
<title lang="en">Visit m3u4u.com</title>
<desc lang="en">Visit m3u4u.com</desc>
</programme>
<programme start="20260131110000 +0000" stop="20260131120000 +0000" channel="m3u4u">
<title lang="en">Visit m3u4u.com</title>
<desc lang="en">Visit m3u4u.com</desc>
</programme>
<programme start="20260131120000 +0000" stop="20260131130000 +0000" channel="m3u4u">
<title lang="en">Visit m3u4u.com</title>
<desc lang="en">Visit m3u4u.com</desc>
</programme>
<programme start="20260131130000 +0000" stop="20260131140000 +0000" channel="m3u4u">
<title lang="en">Visit m3u4u.com</title>
<desc lang="en">Visit m3u4u.com</desc>
</programme>
<programme start="20260131140000 +0000" stop="20260131150000 +0000" channel="m3u4u">
<title lang="en">Visit m3u4u.com</title>
<desc lang="en">Visit m3u4u.com</desc>
</programme>
<programme start="20260131150000 +0000" stop="20260131160000 +0000" channel="m3u4u">
<title lang="en">Visit m3u4u.com</title>
<desc lang="en">Visit m3u4u.com</desc>
</programme>
<programme start="20260131160000 +0000" stop="20260131170000 +0000" channel="m3u4u">
<title lang="en">Visit m3u4u.com</title>
<desc lang="en">Visit m3u4u.com</desc>
</programme>
<programme start="20260131170000 +0000" stop="20260131180000 +0000" channel="m3u4u">
<title lang="en">Visit m3u4u.com</title>
<desc lang="en">Visit m3u4u.com</desc>
</programme>
<programme start="20260131180000 +0000" stop="20260131190000 +0000" channel="m3u4u">
<title lang="en">Visit m3u4u.com</title>
<desc lang="en">Visit m3u4u.com</desc>
</programme>
<programme start="20260131190000 +0000" stop="20260131200000 +0000" channel="m3u4u">
<title lang="en">Visit m3u4u.com</title>
<desc lang="en">Visit m3u4u.com</desc>
</programme>
<programme start="20260131200000 +0000" stop="20260131210000 +0000" channel="m3u4u">
<title lang="en">Visit m3u4u.com</title>
<desc lang="en">Visit m3u4u.com</desc>
</programme>
<programme start="20260131210000 +0000" stop="20260131220000 +0000" channel="m3u4u">
<title lang="en">Visit m3u4u.com</title>
<desc lang="en">Visit m3u4u.com</desc>
</programme>
<programme start="20260131220000 +0000" stop="20260131230000 +0000" channel="m3u4u">
<title lang="en">Visit m3u4u.com</title>
<desc lang="en">Visit m3u4u.com</desc>
</programme>
<programme start="20260131230000 +0000" stop="20260201000000 +0000" channel="m3u4u">
<title lang="en">Visit m3u4u.com</title>
<desc lang="en">Visit m3u4u.com</desc>
</programme>
</tv>