<?xml version="1.0" encoding="UTF-8"?>
<tv generator-info-name="m3u4u" generator-info-url="https://m3u4u.com/">
<channel id="m3u4u">
<display-name>Visit m3u4u.com</display-name>
</channel>
<programme start="20251127000000 +0000" stop="20251127010000 +0000" channel="m3u4u">
<title lang="en">Visit m3u4u.com</title>
<desc lang="en">Visit m3u4u.com</desc>
</programme>
<programme start="20251127010000 +0000" stop="20251127020000 +0000" channel="m3u4u">
<title lang="en">Visit m3u4u.com</title>
<desc lang="en">Visit m3u4u.com</desc>
</programme>
<programme start="20251127020000 +0000" stop="20251127030000 +0000" channel="m3u4u">
<title lang="en">Visit m3u4u.com</title>
<desc lang="en">Visit m3u4u.com</desc>
</programme>
<programme start="20251127030000 +0000" stop="20251127040000 +0000" channel="m3u4u">
<title lang="en">Visit m3u4u.com</title>
<desc lang="en">Visit m3u4u.com</desc>
</programme>
<programme start="20251127040000 +0000" stop="20251127050000 +0000" channel="m3u4u">
<title lang="en">Visit m3u4u.com</title>
<desc lang="en">Visit m3u4u.com</desc>
</programme>
<programme start="20251127050000 +0000" stop="20251127060000 +0000" channel="m3u4u">
<title lang="en">Visit m3u4u.com</title>
<desc lang="en">Visit m3u4u.com</desc>
</programme>
<programme start="20251127060000 +0000" stop="20251127070000 +0000" channel="m3u4u">
<title lang="en">Visit m3u4u.com</title>
<desc lang="en">Visit m3u4u.com</desc>
</programme>
<programme start="20251127070000 +0000" stop="20251127080000 +0000" channel="m3u4u">
<title lang="en">Visit m3u4u.com</title>
<desc lang="en">Visit m3u4u.com</desc>
</programme>
<programme start="20251127080000 +0000" stop="20251127090000 +0000" channel="m3u4u">
<title lang="en">Visit m3u4u.com</title>
<desc lang="en">Visit m3u4u.com</desc>
</programme>
<programme start="20251127090000 +0000" stop="20251127100000 +0000" channel="m3u4u">
<title lang="en">Visit m3u4u.com</title>
<desc lang="en">Visit m3u4u.com</desc>
</programme>
<programme start="20251127100000 +0000" stop="20251127110000 +0000" channel="m3u4u">
<title lang="en">Visit m3u4u.com</title>
<desc lang="en">Visit m3u4u.com</desc>
</programme>
<programme start="20251127110000 +0000" stop="20251127120000 +0000" channel="m3u4u">
<title lang="en">Visit m3u4u.com</title>
<desc lang="en">Visit m3u4u.com</desc>
</programme>
<programme start="20251127120000 +0000" stop="20251127130000 +0000" channel="m3u4u">
<title lang="en">Visit m3u4u.com</title>
<desc lang="en">Visit m3u4u.com</desc>
</programme>
<programme start="20251127130000 +0000" stop="20251127140000 +0000" channel="m3u4u">
<title lang="en">Visit m3u4u.com</title>
<desc lang="en">Visit m3u4u.com</desc>
</programme>
<programme start="20251127140000 +0000" stop="20251127150000 +0000" channel="m3u4u">
<title lang="en">Visit m3u4u.com</title>
<desc lang="en">Visit m3u4u.com</desc>
</programme>
<programme start="20251127150000 +0000" stop="20251127160000 +0000" channel="m3u4u">
<title lang="en">Visit m3u4u.com</title>
<desc lang="en">Visit m3u4u.com</desc>
</programme>
<programme start="20251127160000 +0000" stop="20251127170000 +0000" channel="m3u4u">
<title lang="en">Visit m3u4u.com</title>
<desc lang="en">Visit m3u4u.com</desc>
</programme>
<programme start="20251127170000 +0000" stop="20251127180000 +0000" channel="m3u4u">
<title lang="en">Visit m3u4u.com</title>
<desc lang="en">Visit m3u4u.com</desc>
</programme>
<programme start="20251127180000 +0000" stop="20251127190000 +0000" channel="m3u4u">
<title lang="en">Visit m3u4u.com</title>
<desc lang="en">Visit m3u4u.com</desc>
</programme>
<programme start="20251127190000 +0000" stop="20251127200000 +0000" channel="m3u4u">
<title lang="en">Visit m3u4u.com</title>
<desc lang="en">Visit m3u4u.com</desc>
</programme>
<programme start="20251127200000 +0000" stop="20251127210000 +0000" channel="m3u4u">
<title lang="en">Visit m3u4u.com</title>
<desc lang="en">Visit m3u4u.com</desc>
</programme>
<programme start="20251127210000 +0000" stop="20251127220000 +0000" channel="m3u4u">
<title lang="en">Visit m3u4u.com</title>
<desc lang="en">Visit m3u4u.com</desc>
</programme>
<programme start="20251127220000 +0000" stop="20251127230000 +0000" channel="m3u4u">
<title lang="en">Visit m3u4u.com</title>
<desc lang="en">Visit m3u4u.com</desc>
</programme>
<programme start="20251127230000 +0000" stop="20251128000000 +0000" channel="m3u4u">
<title lang="en">Visit m3u4u.com</title>
<desc lang="en">Visit m3u4u.com</desc>
</programme>
<programme start="20251128000000 +0000" stop="20251128010000 +0000" channel="m3u4u">
<title lang="en">Visit m3u4u.com</title>
<desc lang="en">Visit m3u4u.com</desc>
</programme>
<programme start="20251128010000 +0000" stop="20251128020000 +0000" channel="m3u4u">
<title lang="en">Visit m3u4u.com</title>
<desc lang="en">Visit m3u4u.com</desc>
</programme>
<programme start="20251128020000 +0000" stop="20251128030000 +0000" channel="m3u4u">
<title lang="en">Visit m3u4u.com</title>
<desc lang="en">Visit m3u4u.com</desc>
</programme>
<programme start="20251128030000 +0000" stop="20251128040000 +0000" channel="m3u4u">
<title lang="en">Visit m3u4u.com</title>
<desc lang="en">Visit m3u4u.com</desc>
</programme>
<programme start="20251128040000 +0000" stop="20251128050000 +0000" channel="m3u4u">
<title lang="en">Visit m3u4u.com</title>
<desc lang="en">Visit m3u4u.com</desc>
</programme>
<programme start="20251128050000 +0000" stop="20251128060000 +0000" channel="m3u4u">
<title lang="en">Visit m3u4u.com</title>
<desc lang="en">Visit m3u4u.com</desc>
</programme>
<programme start="20251128060000 +0000" stop="20251128070000 +0000" channel="m3u4u">
<title lang="en">Visit m3u4u.com</title>
<desc lang="en">Visit m3u4u.com</desc>
</programme>
<programme start="20251128070000 +0000" stop="20251128080000 +0000" channel="m3u4u">
<title lang="en">Visit m3u4u.com</title>
<desc lang="en">Visit m3u4u.com</desc>
</programme>
<programme start="20251128080000 +0000" stop="20251128090000 +0000" channel="m3u4u">
<title lang="en">Visit m3u4u.com</title>
<desc lang="en">Visit m3u4u.com</desc>
</programme>
<programme start="20251128090000 +0000" stop="20251128100000 +0000" channel="m3u4u">
<title lang="en">Visit m3u4u.com</title>
<desc lang="en">Visit m3u4u.com</desc>
</programme>
<programme start="20251128100000 +0000" stop="20251128110000 +0000" channel="m3u4u">
<title lang="en">Visit m3u4u.com</title>
<desc lang="en">Visit m3u4u.com</desc>
</programme>
<programme start="20251128110000 +0000" stop="20251128120000 +0000" channel="m3u4u">
<title lang="en">Visit m3u4u.com</title>
<desc lang="en">Visit m3u4u.com</desc>
</programme>
<programme start="20251128120000 +0000" stop="20251128130000 +0000" channel="m3u4u">
<title lang="en">Visit m3u4u.com</title>
<desc lang="en">Visit m3u4u.com</desc>
</programme>
<programme start="20251128130000 +0000" stop="20251128140000 +0000" channel="m3u4u">
<title lang="en">Visit m3u4u.com</title>
<desc lang="en">Visit m3u4u.com</desc>
</programme>
<programme start="20251128140000 +0000" stop="20251128150000 +0000" channel="m3u4u">
<title lang="en">Visit m3u4u.com</title>
<desc lang="en">Visit m3u4u.com</desc>
</programme>
<programme start="20251128150000 +0000" stop="20251128160000 +0000" channel="m3u4u">
<title lang="en">Visit m3u4u.com</title>
<desc lang="en">Visit m3u4u.com</desc>
</programme>
<programme start="20251128160000 +0000" stop="20251128170000 +0000" channel="m3u4u">
<title lang="en">Visit m3u4u.com</title>
<desc lang="en">Visit m3u4u.com</desc>
</programme>
<programme start="20251128170000 +0000" stop="20251128180000 +0000" channel="m3u4u">
<title lang="en">Visit m3u4u.com</title>
<desc lang="en">Visit m3u4u.com</desc>
</programme>
<programme start="20251128180000 +0000" stop="20251128190000 +0000" channel="m3u4u">
<title lang="en">Visit m3u4u.com</title>
<desc lang="en">Visit m3u4u.com</desc>
</programme>
<programme start="20251128190000 +0000" stop="20251128200000 +0000" channel="m3u4u">
<title lang="en">Visit m3u4u.com</title>
<desc lang="en">Visit m3u4u.com</desc>
</programme>
<programme start="20251128200000 +0000" stop="20251128210000 +0000" channel="m3u4u">
<title lang="en">Visit m3u4u.com</title>
<desc lang="en">Visit m3u4u.com</desc>
</programme>
<programme start="20251128210000 +0000" stop="20251128220000 +0000" channel="m3u4u">
<title lang="en">Visit m3u4u.com</title>
<desc lang="en">Visit m3u4u.com</desc>
</programme>
<programme start="20251128220000 +0000" stop="20251128230000 +0000" channel="m3u4u">
<title lang="en">Visit m3u4u.com</title>
<desc lang="en">Visit m3u4u.com</desc>
</programme>
<programme start="20251128230000 +0000" stop="20251129000000 +0000" channel="m3u4u">
<title lang="en">Visit m3u4u.com</title>
<desc lang="en">Visit m3u4u.com</desc>
</programme>
<programme start="20251129000000 +0000" stop="20251129010000 +0000" channel="m3u4u">
<title lang="en">Visit m3u4u.com</title>
<desc lang="en">Visit m3u4u.com</desc>
</programme>
<programme start="20251129010000 +0000" stop="20251129020000 +0000" channel="m3u4u">
<title lang="en">Visit m3u4u.com</title>
<desc lang="en">Visit m3u4u.com</desc>
</programme>
<programme start="20251129020000 +0000" stop="20251129030000 +0000" channel="m3u4u">
<title lang="en">Visit m3u4u.com</title>
<desc lang="en">Visit m3u4u.com</desc>
</programme>
<programme start="20251129030000 +0000" stop="20251129040000 +0000" channel="m3u4u">
<title lang="en">Visit m3u4u.com</title>
<desc lang="en">Visit m3u4u.com</desc>
</programme>
<programme start="20251129040000 +0000" stop="20251129050000 +0000" channel="m3u4u">
<title lang="en">Visit m3u4u.com</title>
<desc lang="en">Visit m3u4u.com</desc>
</programme>
<programme start="20251129050000 +0000" stop="20251129060000 +0000" channel="m3u4u">
<title lang="en">Visit m3u4u.com</title>
<desc lang="en">Visit m3u4u.com</desc>
</programme>
<programme start="20251129060000 +0000" stop="20251129070000 +0000" channel="m3u4u">
<title lang="en">Visit m3u4u.com</title>
<desc lang="en">Visit m3u4u.com</desc>
</programme>
<programme start="20251129070000 +0000" stop="20251129080000 +0000" channel="m3u4u">
<title lang="en">Visit m3u4u.com</title>
<desc lang="en">Visit m3u4u.com</desc>
</programme>
<programme start="20251129080000 +0000" stop="20251129090000 +0000" channel="m3u4u">
<title lang="en">Visit m3u4u.com</title>
<desc lang="en">Visit m3u4u.com</desc>
</programme>
<programme start="20251129090000 +0000" stop="20251129100000 +0000" channel="m3u4u">
<title lang="en">Visit m3u4u.com</title>
<desc lang="en">Visit m3u4u.com</desc>
</programme>
<programme start="20251129100000 +0000" stop="20251129110000 +0000" channel="m3u4u">
<title lang="en">Visit m3u4u.com</title>
<desc lang="en">Visit m3u4u.com</desc>
</programme>
<programme start="20251129110000 +0000" stop="20251129120000 +0000" channel="m3u4u">
<title lang="en">Visit m3u4u.com</title>
<desc lang="en">Visit m3u4u.com</desc>
</programme>
<programme start="20251129120000 +0000" stop="20251129130000 +0000" channel="m3u4u">
<title lang="en">Visit m3u4u.com</title>
<desc lang="en">Visit m3u4u.com</desc>
</programme>
<programme start="20251129130000 +0000" stop="20251129140000 +0000" channel="m3u4u">
<title lang="en">Visit m3u4u.com</title>
<desc lang="en">Visit m3u4u.com</desc>
</programme>
<programme start="20251129140000 +0000" stop="20251129150000 +0000" channel="m3u4u">
<title lang="en">Visit m3u4u.com</title>
<desc lang="en">Visit m3u4u.com</desc>
</programme>
<programme start="20251129150000 +0000" stop="20251129160000 +0000" channel="m3u4u">
<title lang="en">Visit m3u4u.com</title>
<desc lang="en">Visit m3u4u.com</desc>
</programme>
<programme start="20251129160000 +0000" stop="20251129170000 +0000" channel="m3u4u">
<title lang="en">Visit m3u4u.com</title>
<desc lang="en">Visit m3u4u.com</desc>
</programme>
<programme start="20251129170000 +0000" stop="20251129180000 +0000" channel="m3u4u">
<title lang="en">Visit m3u4u.com</title>
<desc lang="en">Visit m3u4u.com</desc>
</programme>
<programme start="20251129180000 +0000" stop="20251129190000 +0000" channel="m3u4u">
<title lang="en">Visit m3u4u.com</title>
<desc lang="en">Visit m3u4u.com</desc>
</programme>
<programme start="20251129190000 +0000" stop="20251129200000 +0000" channel="m3u4u">
<title lang="en">Visit m3u4u.com</title>
<desc lang="en">Visit m3u4u.com</desc>
</programme>
<programme start="20251129200000 +0000" stop="20251129210000 +0000" channel="m3u4u">
<title lang="en">Visit m3u4u.com</title>
<desc lang="en">Visit m3u4u.com</desc>
</programme>
<programme start="20251129210000 +0000" stop="20251129220000 +0000" channel="m3u4u">
<title lang="en">Visit m3u4u.com</title>
<desc lang="en">Visit m3u4u.com</desc>
</programme>
<programme start="20251129220000 +0000" stop="20251129230000 +0000" channel="m3u4u">
<title lang="en">Visit m3u4u.com</title>
<desc lang="en">Visit m3u4u.com</desc>
</programme>
<programme start="20251129230000 +0000" stop="20251130000000 +0000" channel="m3u4u">
<title lang="en">Visit m3u4u.com</title>
<desc lang="en">Visit m3u4u.com</desc>
</programme>
</tv>