<?xml version="1.0" encoding="UTF-8"?>
<tv generator-info-name="m3u4u" generator-info-url="https://m3u4u.com/">
<channel id="m3u4u">
<display-name>Visit m3u4u.com</display-name>
</channel>
<programme start="20251104000000 +0000" stop="20251104010000 +0000" channel="m3u4u">
<title lang="en">Visit m3u4u.com</title>
<desc lang="en">Visit m3u4u.com</desc>
</programme>
<programme start="20251104010000 +0000" stop="20251104020000 +0000" channel="m3u4u">
<title lang="en">Visit m3u4u.com</title>
<desc lang="en">Visit m3u4u.com</desc>
</programme>
<programme start="20251104020000 +0000" stop="20251104030000 +0000" channel="m3u4u">
<title lang="en">Visit m3u4u.com</title>
<desc lang="en">Visit m3u4u.com</desc>
</programme>
<programme start="20251104030000 +0000" stop="20251104040000 +0000" channel="m3u4u">
<title lang="en">Visit m3u4u.com</title>
<desc lang="en">Visit m3u4u.com</desc>
</programme>
<programme start="20251104040000 +0000" stop="20251104050000 +0000" channel="m3u4u">
<title lang="en">Visit m3u4u.com</title>
<desc lang="en">Visit m3u4u.com</desc>
</programme>
<programme start="20251104050000 +0000" stop="20251104060000 +0000" channel="m3u4u">
<title lang="en">Visit m3u4u.com</title>
<desc lang="en">Visit m3u4u.com</desc>
</programme>
<programme start="20251104060000 +0000" stop="20251104070000 +0000" channel="m3u4u">
<title lang="en">Visit m3u4u.com</title>
<desc lang="en">Visit m3u4u.com</desc>
</programme>
<programme start="20251104070000 +0000" stop="20251104080000 +0000" channel="m3u4u">
<title lang="en">Visit m3u4u.com</title>
<desc lang="en">Visit m3u4u.com</desc>
</programme>
<programme start="20251104080000 +0000" stop="20251104090000 +0000" channel="m3u4u">
<title lang="en">Visit m3u4u.com</title>
<desc lang="en">Visit m3u4u.com</desc>
</programme>
<programme start="20251104090000 +0000" stop="20251104100000 +0000" channel="m3u4u">
<title lang="en">Visit m3u4u.com</title>
<desc lang="en">Visit m3u4u.com</desc>
</programme>
<programme start="20251104100000 +0000" stop="20251104110000 +0000" channel="m3u4u">
<title lang="en">Visit m3u4u.com</title>
<desc lang="en">Visit m3u4u.com</desc>
</programme>
<programme start="20251104110000 +0000" stop="20251104120000 +0000" channel="m3u4u">
<title lang="en">Visit m3u4u.com</title>
<desc lang="en">Visit m3u4u.com</desc>
</programme>
<programme start="20251104120000 +0000" stop="20251104130000 +0000" channel="m3u4u">
<title lang="en">Visit m3u4u.com</title>
<desc lang="en">Visit m3u4u.com</desc>
</programme>
<programme start="20251104130000 +0000" stop="20251104140000 +0000" channel="m3u4u">
<title lang="en">Visit m3u4u.com</title>
<desc lang="en">Visit m3u4u.com</desc>
</programme>
<programme start="20251104140000 +0000" stop="20251104150000 +0000" channel="m3u4u">
<title lang="en">Visit m3u4u.com</title>
<desc lang="en">Visit m3u4u.com</desc>
</programme>
<programme start="20251104150000 +0000" stop="20251104160000 +0000" channel="m3u4u">
<title lang="en">Visit m3u4u.com</title>
<desc lang="en">Visit m3u4u.com</desc>
</programme>
<programme start="20251104160000 +0000" stop="20251104170000 +0000" channel="m3u4u">
<title lang="en">Visit m3u4u.com</title>
<desc lang="en">Visit m3u4u.com</desc>
</programme>
<programme start="20251104170000 +0000" stop="20251104180000 +0000" channel="m3u4u">
<title lang="en">Visit m3u4u.com</title>
<desc lang="en">Visit m3u4u.com</desc>
</programme>
<programme start="20251104180000 +0000" stop="20251104190000 +0000" channel="m3u4u">
<title lang="en">Visit m3u4u.com</title>
<desc lang="en">Visit m3u4u.com</desc>
</programme>
<programme start="20251104190000 +0000" stop="20251104200000 +0000" channel="m3u4u">
<title lang="en">Visit m3u4u.com</title>
<desc lang="en">Visit m3u4u.com</desc>
</programme>
<programme start="20251104200000 +0000" stop="20251104210000 +0000" channel="m3u4u">
<title lang="en">Visit m3u4u.com</title>
<desc lang="en">Visit m3u4u.com</desc>
</programme>
<programme start="20251104210000 +0000" stop="20251104220000 +0000" channel="m3u4u">
<title lang="en">Visit m3u4u.com</title>
<desc lang="en">Visit m3u4u.com</desc>
</programme>
<programme start="20251104220000 +0000" stop="20251104230000 +0000" channel="m3u4u">
<title lang="en">Visit m3u4u.com</title>
<desc lang="en">Visit m3u4u.com</desc>
</programme>
<programme start="20251104230000 +0000" stop="20251105000000 +0000" channel="m3u4u">
<title lang="en">Visit m3u4u.com</title>
<desc lang="en">Visit m3u4u.com</desc>
</programme>
<programme start="20251105000000 +0000" stop="20251105010000 +0000" channel="m3u4u">
<title lang="en">Visit m3u4u.com</title>
<desc lang="en">Visit m3u4u.com</desc>
</programme>
<programme start="20251105010000 +0000" stop="20251105020000 +0000" channel="m3u4u">
<title lang="en">Visit m3u4u.com</title>
<desc lang="en">Visit m3u4u.com</desc>
</programme>
<programme start="20251105020000 +0000" stop="20251105030000 +0000" channel="m3u4u">
<title lang="en">Visit m3u4u.com</title>
<desc lang="en">Visit m3u4u.com</desc>
</programme>
<programme start="20251105030000 +0000" stop="20251105040000 +0000" channel="m3u4u">
<title lang="en">Visit m3u4u.com</title>
<desc lang="en">Visit m3u4u.com</desc>
</programme>
<programme start="20251105040000 +0000" stop="20251105050000 +0000" channel="m3u4u">
<title lang="en">Visit m3u4u.com</title>
<desc lang="en">Visit m3u4u.com</desc>
</programme>
<programme start="20251105050000 +0000" stop="20251105060000 +0000" channel="m3u4u">
<title lang="en">Visit m3u4u.com</title>
<desc lang="en">Visit m3u4u.com</desc>
</programme>
<programme start="20251105060000 +0000" stop="20251105070000 +0000" channel="m3u4u">
<title lang="en">Visit m3u4u.com</title>
<desc lang="en">Visit m3u4u.com</desc>
</programme>
<programme start="20251105070000 +0000" stop="20251105080000 +0000" channel="m3u4u">
<title lang="en">Visit m3u4u.com</title>
<desc lang="en">Visit m3u4u.com</desc>
</programme>
<programme start="20251105080000 +0000" stop="20251105090000 +0000" channel="m3u4u">
<title lang="en">Visit m3u4u.com</title>
<desc lang="en">Visit m3u4u.com</desc>
</programme>
<programme start="20251105090000 +0000" stop="20251105100000 +0000" channel="m3u4u">
<title lang="en">Visit m3u4u.com</title>
<desc lang="en">Visit m3u4u.com</desc>
</programme>
<programme start="20251105100000 +0000" stop="20251105110000 +0000" channel="m3u4u">
<title lang="en">Visit m3u4u.com</title>
<desc lang="en">Visit m3u4u.com</desc>
</programme>
<programme start="20251105110000 +0000" stop="20251105120000 +0000" channel="m3u4u">
<title lang="en">Visit m3u4u.com</title>
<desc lang="en">Visit m3u4u.com</desc>
</programme>
<programme start="20251105120000 +0000" stop="20251105130000 +0000" channel="m3u4u">
<title lang="en">Visit m3u4u.com</title>
<desc lang="en">Visit m3u4u.com</desc>
</programme>
<programme start="20251105130000 +0000" stop="20251105140000 +0000" channel="m3u4u">
<title lang="en">Visit m3u4u.com</title>
<desc lang="en">Visit m3u4u.com</desc>
</programme>
<programme start="20251105140000 +0000" stop="20251105150000 +0000" channel="m3u4u">
<title lang="en">Visit m3u4u.com</title>
<desc lang="en">Visit m3u4u.com</desc>
</programme>
<programme start="20251105150000 +0000" stop="20251105160000 +0000" channel="m3u4u">
<title lang="en">Visit m3u4u.com</title>
<desc lang="en">Visit m3u4u.com</desc>
</programme>
<programme start="20251105160000 +0000" stop="20251105170000 +0000" channel="m3u4u">
<title lang="en">Visit m3u4u.com</title>
<desc lang="en">Visit m3u4u.com</desc>
</programme>
<programme start="20251105170000 +0000" stop="20251105180000 +0000" channel="m3u4u">
<title lang="en">Visit m3u4u.com</title>
<desc lang="en">Visit m3u4u.com</desc>
</programme>
<programme start="20251105180000 +0000" stop="20251105190000 +0000" channel="m3u4u">
<title lang="en">Visit m3u4u.com</title>
<desc lang="en">Visit m3u4u.com</desc>
</programme>
<programme start="20251105190000 +0000" stop="20251105200000 +0000" channel="m3u4u">
<title lang="en">Visit m3u4u.com</title>
<desc lang="en">Visit m3u4u.com</desc>
</programme>
<programme start="20251105200000 +0000" stop="20251105210000 +0000" channel="m3u4u">
<title lang="en">Visit m3u4u.com</title>
<desc lang="en">Visit m3u4u.com</desc>
</programme>
<programme start="20251105210000 +0000" stop="20251105220000 +0000" channel="m3u4u">
<title lang="en">Visit m3u4u.com</title>
<desc lang="en">Visit m3u4u.com</desc>
</programme>
<programme start="20251105220000 +0000" stop="20251105230000 +0000" channel="m3u4u">
<title lang="en">Visit m3u4u.com</title>
<desc lang="en">Visit m3u4u.com</desc>
</programme>
<programme start="20251105230000 +0000" stop="20251106000000 +0000" channel="m3u4u">
<title lang="en">Visit m3u4u.com</title>
<desc lang="en">Visit m3u4u.com</desc>
</programme>
<programme start="20251106000000 +0000" stop="20251106010000 +0000" channel="m3u4u">
<title lang="en">Visit m3u4u.com</title>
<desc lang="en">Visit m3u4u.com</desc>
</programme>
<programme start="20251106010000 +0000" stop="20251106020000 +0000" channel="m3u4u">
<title lang="en">Visit m3u4u.com</title>
<desc lang="en">Visit m3u4u.com</desc>
</programme>
<programme start="20251106020000 +0000" stop="20251106030000 +0000" channel="m3u4u">
<title lang="en">Visit m3u4u.com</title>
<desc lang="en">Visit m3u4u.com</desc>
</programme>
<programme start="20251106030000 +0000" stop="20251106040000 +0000" channel="m3u4u">
<title lang="en">Visit m3u4u.com</title>
<desc lang="en">Visit m3u4u.com</desc>
</programme>
<programme start="20251106040000 +0000" stop="20251106050000 +0000" channel="m3u4u">
<title lang="en">Visit m3u4u.com</title>
<desc lang="en">Visit m3u4u.com</desc>
</programme>
<programme start="20251106050000 +0000" stop="20251106060000 +0000" channel="m3u4u">
<title lang="en">Visit m3u4u.com</title>
<desc lang="en">Visit m3u4u.com</desc>
</programme>
<programme start="20251106060000 +0000" stop="20251106070000 +0000" channel="m3u4u">
<title lang="en">Visit m3u4u.com</title>
<desc lang="en">Visit m3u4u.com</desc>
</programme>
<programme start="20251106070000 +0000" stop="20251106080000 +0000" channel="m3u4u">
<title lang="en">Visit m3u4u.com</title>
<desc lang="en">Visit m3u4u.com</desc>
</programme>
<programme start="20251106080000 +0000" stop="20251106090000 +0000" channel="m3u4u">
<title lang="en">Visit m3u4u.com</title>
<desc lang="en">Visit m3u4u.com</desc>
</programme>
<programme start="20251106090000 +0000" stop="20251106100000 +0000" channel="m3u4u">
<title lang="en">Visit m3u4u.com</title>
<desc lang="en">Visit m3u4u.com</desc>
</programme>
<programme start="20251106100000 +0000" stop="20251106110000 +0000" channel="m3u4u">
<title lang="en">Visit m3u4u.com</title>
<desc lang="en">Visit m3u4u.com</desc>
</programme>
<programme start="20251106110000 +0000" stop="20251106120000 +0000" channel="m3u4u">
<title lang="en">Visit m3u4u.com</title>
<desc lang="en">Visit m3u4u.com</desc>
</programme>
<programme start="20251106120000 +0000" stop="20251106130000 +0000" channel="m3u4u">
<title lang="en">Visit m3u4u.com</title>
<desc lang="en">Visit m3u4u.com</desc>
</programme>
<programme start="20251106130000 +0000" stop="20251106140000 +0000" channel="m3u4u">
<title lang="en">Visit m3u4u.com</title>
<desc lang="en">Visit m3u4u.com</desc>
</programme>
<programme start="20251106140000 +0000" stop="20251106150000 +0000" channel="m3u4u">
<title lang="en">Visit m3u4u.com</title>
<desc lang="en">Visit m3u4u.com</desc>
</programme>
<programme start="20251106150000 +0000" stop="20251106160000 +0000" channel="m3u4u">
<title lang="en">Visit m3u4u.com</title>
<desc lang="en">Visit m3u4u.com</desc>
</programme>
<programme start="20251106160000 +0000" stop="20251106170000 +0000" channel="m3u4u">
<title lang="en">Visit m3u4u.com</title>
<desc lang="en">Visit m3u4u.com</desc>
</programme>
<programme start="20251106170000 +0000" stop="20251106180000 +0000" channel="m3u4u">
<title lang="en">Visit m3u4u.com</title>
<desc lang="en">Visit m3u4u.com</desc>
</programme>
<programme start="20251106180000 +0000" stop="20251106190000 +0000" channel="m3u4u">
<title lang="en">Visit m3u4u.com</title>
<desc lang="en">Visit m3u4u.com</desc>
</programme>
<programme start="20251106190000 +0000" stop="20251106200000 +0000" channel="m3u4u">
<title lang="en">Visit m3u4u.com</title>
<desc lang="en">Visit m3u4u.com</desc>
</programme>
<programme start="20251106200000 +0000" stop="20251106210000 +0000" channel="m3u4u">
<title lang="en">Visit m3u4u.com</title>
<desc lang="en">Visit m3u4u.com</desc>
</programme>
<programme start="20251106210000 +0000" stop="20251106220000 +0000" channel="m3u4u">
<title lang="en">Visit m3u4u.com</title>
<desc lang="en">Visit m3u4u.com</desc>
</programme>
<programme start="20251106220000 +0000" stop="20251106230000 +0000" channel="m3u4u">
<title lang="en">Visit m3u4u.com</title>
<desc lang="en">Visit m3u4u.com</desc>
</programme>
<programme start="20251106230000 +0000" stop="20251107000000 +0000" channel="m3u4u">
<title lang="en">Visit m3u4u.com</title>
<desc lang="en">Visit m3u4u.com</desc>
</programme>
</tv>